README.rst
setup.py
django_gulp_rev.egg-info/PKG-INFO
django_gulp_rev.egg-info/SOURCES.txt
django_gulp_rev.egg-info/dependency_links.txt
django_gulp_rev.egg-info/top_level.txt
gulp_rev/__init__.py
gulp_rev/templatetags/__init__.py
gulp_rev/templatetags/rev.py
gulp_rev/tests/__init__.py
gulp_rev/tests/tests.py
test_app/__init__.py
test_app/settings.py
test_app/urls.py