Metadata-Version: 1.1
Name: django-gulp-rev
Version: 0.2
Summary: A simple Django integration with gulp-rev
Home-page: https://github.com/olasitarska/django-gulp-rev/
Author: Ola Sitarska
Author-email: ola@sitarska.com
License: BSD License
Platform: UNKNOWN
Classifier: Environment :: Web Environment
Classifier: Framework :: Django
Classifier: Framework :: Django :: 1.8
Classifier: Framework :: Django :: 1.9
Classifier: Intended Audience :: Developers
Classifier: License :: OSI Approved :: BSD License
Classifier: Operating System :: OS Independent
Classifier: Programming Language :: Python
